sshkey_switch/__init__.py
sshkey_switch/main.py
sshkey_switch-0.4.0.dist-info/LICENSE
sshkey_switch-0.4.0.dist-info/METADATA
sshkey_switch-0.4.0.dist-info/WHEEL
sshkey_switch-0.4.0.dist-info/entry_points.txt
sshkey_switch-0.4.0.dist-info/top_level.txt
sshkey_switch-0.4.0.dist-info/RECORD
