Metadata-Version: 2.2
Name: sshkey-switch
Version: 0.4.0
Summary: A command-line tool for switching SSH keys
Author-email: Ramkumar Manickam <ramkumarm.eng@gmail.com>
License: MIT
Project-URL: Homepage, https://github.com/mramkumar/sshkey-switch
Requires-Python: >=3.0
License-File: LICENSE
Requires-Dist: questionary
